gradient_descent/__init__.py
gradient_descent/loss_functions.py
gradient_descent/optimizers.py
gradient_descent/utils.py
gradient_descentbjk-0.1.0.dist-info/METADATA
gradient_descentbjk-0.1.0.dist-info/WHEEL
gradient_descentbjk-0.1.0.dist-info/top_level.txt
gradient_descentbjk-0.1.0.dist-info/RECORD
