Metadata-Version: 2.4
Name: gradient_descentbjk
Version: 0.1.0
Summary: A Python package implementing various gradient descent optimization algorithms
Home-page: https://github.com/Jordan-buwa/gradient_descent
Author: Jordan Buwa
Author-email: jmbouobda@aimsammi.org
Keywords: machine learning,optimization,gradient descent,neural networks
Classifier: Development Status :: 3 - Alpha
Classifier: Intended Audience :: Developers
Classifier: Intended Audience :: Science/Research
Classifier: License :: OSI Approved :: MIT License
Classifier: Programming Language :: Python :: 3
Classifier: Programming Language :: Python :: 3.7
Classifier: Programming Language :: Python :: 3.8
Classifier: Programming Language :: Python :: 3.9
Classifier: Topic :: Scientific/Engineering
Classifier: Topic :: Scientific/Engineering :: Artificial Intelligence
Classifier: Topic :: Scientific/Engineering :: Mathematics
Requires-Python: >=3.7
Requires-Dist: numpy>=1.19.0
Requires-Dist: matplotlib>=3.3.0
Dynamic: author
Dynamic: author-email
Dynamic: classifier
Dynamic: home-page
Dynamic: keywords
Dynamic: requires-dist
Dynamic: requires-python
Dynamic: summary
